shalchemy/__init__.py
shalchemy/arguments.py
shalchemy/bin.py
shalchemy/expressions.py
shalchemy/probe.py
shalchemy/run_result.py
shalchemy/runner.py
shalchemy/types.py
shalchemy/test/__init__.py
shalchemy/test/base.py
shalchemy/test/test_arguments.py
shalchemy/test/test_overall.py
shalchemy/test/test_redirection.py
shalchemy/test/test_substitution.py
shalchemy-1.0.1.dist-info/LICENSE
shalchemy-1.0.1.dist-info/METADATA
shalchemy-1.0.1.dist-info/WHEEL
shalchemy-1.0.1.dist-info/entry_points.txt
shalchemy-1.0.1.dist-info/top_level.txt
shalchemy-1.0.1.dist-info/RECORD
