Metadata-Version: 2.1
Name: shalchemy
Version: 1.0.1
Summary: A shell scripting toolkit for Python
Home-page: https://github.com/mechaform/shalchemy
Author: Payton Yao
Author-email: payton.yao@gmail.com
License: MIT
Keywords: sh shell bash
Platform: UNKNOWN
Classifier: License :: OSI Approved :: MIT License
License-File: LICENSE
